django_jsrender-0.2.dist-info/DESCRIPTION.rst
django_jsrender-0.2.dist-info/METADATA
django_jsrender-0.2.dist-info/RECORD
django_jsrender-0.2.dist-info/WHEEL
django_jsrender-0.2.dist-info/metadata.json
django_jsrender-0.2.dist-info/top_level.txt
jsrender/__init__.py
jsrender/context.py
jsrender/datetimeformat.py
jsrender/filters.py
jsrender/functions.py
jsrender/tags.py
jsrender/translate.py
jsrender/utils.py
jsrender/templates/jsrender/html_escape.html
jsrender/templates/jsrender/html_escape.js
jsrender/templatetags/__init__.py
jsrender/templatetags/jsrender.py
jsrender/tests/__init__.py
jsrender/tests/filters.py
jsrender/tests/functions.py
jsrender/tests/tags.py
jsrender/tests/templatetag.py
jsrender/tests/translate.py
jsrender/tests/utils.py
jsrender/tests/utiltests.py
