Metadata-Version: 2.0
Name: django-jsrender
Version: 0.2
Summary: Render Django templates into Javascript functions.
Home-page: https://github.com/AJHMvR/django-jsrender
Author: Alexander van Ratingen
Author-email: alexander@van-ratingen.nl
License: UNKNOWN
Platform: UNKNOWN
Classifier: Operating System :: OS Independent
Classifier: Programming Language :: Python
Classifier: Programming Language :: Python :: 2
Classifier: Programming Language :: Python :: 3
Classifier: Environment :: Web Environment
Classifier: Framework :: Django
Classifier: Development Status :: 4 - Beta
Classifier: Intended Audience :: Developers
Classifier: License :: OSI Approved :: GNU General Public License v3 (GPLv3)
Requires-Dist: django (>=1.8)
Requires-Dist: six
